[
  {
    "FirstName": "LORRAINE",
    "LastName": "SULLIVAN",
    "Address": "34 Agave",
    "Secondary Address": "",
    "City": "Lake Forest",
    "State": "CA",
    "County": "Orange",
    "Zip": 92630,
    "Number1": 9496366312
  },
  {
    "FirstName": "NADINE",
    "LastName": "SUMMERFORD",
    "Address": "1724 Pecos Riv",
    "Secondary Address": "",
    "City": "Placentia",
    "State": "CA",
    "County": "Orange",
    "Zip": 92870,
    "Number1": 7145246747
  },
  {
    "FirstName": "HOP",
    "LastName": "TRAN",
    "Address": "16056 Challis St",
    "Secondary Address": "",
    "City": "Fountain Vly",
    "State": "CA",
    "County": "Orange",
    "Zip": 92708,
    "Number1": 7148555268
  },
  {
    "FirstName": "DRAKE",
    "LastName": "LETCHER",
    "Address": "8412 Sterling Way",
    "Secondary Address": "",
    "City": "Westminster",
    "State": "CA",
    "County": "Orange",
    "Zip": 92683,
    "Number1": 7148981666
  },
  {
    "FirstName": "KRISTIN",
    "LastName": "WEBB",
    "Address": "1810 Delaware St",
    "Secondary Address": "",
    "City": "Huntingtn Bch",
    "State": "CA",
    "County": "Orange",
    "Zip": 92648,
    "Number1": 7147170258
  },
  {
    "FirstName": "TRUNG",
    "LastName": "VAN TRAN",
    "Address": "506 W Ash Ave",
    "Secondary Address": "",
    "City": "Fullerton",
    "State": "CA",
    "County": "Orange",
    "Zip": 92832,
    "Number1": 7144589502
  },
  {
    "FirstName": "PATRICK",
    "LastName": "GALLAGHER",
    "Address": "7650 E Big Canyon Dr",
    "Secondary Address": "",
    "City": "Anaheim",
    "State": "CA",
    "County": "Orange",
    "Zip": 92808,
    "Number1": 7142801630
  },
  {
    "FirstName": "ROSALVA",
    "LastName": "HERNANDEZ",
    "Address": "837 S Corta Dr",
    "Secondary Address": "",
    "City": "Santa Ana",
    "State": "CA",
    "County": "Orange",
    "Zip": 92704,
    "Number1": 7146975175
  },
  {
    "FirstName": "DIAN",
    "LastName": "BAZZELL",
    "Address": "20821 Hunter Ln",
    "Secondary Address": "",
    "City": "Huntingtn Bch",
    "State": "CA",
    "County": "Orange",
    "Zip": 92646,
    "Number1": 7149688394
  },
  {
    "FirstName": "WENDY",
    "LastName": "SAMPSON",
    "Address": "17 Misty Mdws",
    "Secondary Address": "",
    "City": "Irvine",
    "State": "CA",
    "County": "Orange",
    "Zip": 92612,
    "Number1": 9493874688
  },
  {
    "FirstName": "ANTHONY",
    "LastName": "PHAM",
    "Address": "11640 Poppy Ave",
    "Secondary Address": "",
    "City": "Fountain Vly",
    "State": "CA",
    "County": "Orange",
    "Zip": 92708,
    "Number1": 7143604019
  },
  {
    "FirstName": "JAMES",
    "LastName": "KILBOURNE",
    "Address": "3 Portsmouth Pl",
    "Secondary Address": "",
    "City": "Trabuco Cyn",
    "State": "CA",
    "County": "Orange",
    "Zip": 92679,
    "Number1": 9498745480
  },
  {
    "FirstName": "BRIAN",
    "LastName": "UYEDA",
    "Address": "26 Los Indios",
    "Secondary Address": "",
    "City": "Irvine",
    "State": "CA",
    "County": "Orange",
    "Zip": 92618,
    "Number1": 9496900600
  },
  {
    "FirstName": "GAIL",
    "LastName": "MELTEBARGER",
    "Address": "11671 Gary St",
    "Secondary Address": "",
    "City": "Garden Grove",
    "State": "CA",
    "County": "Orange",
    "Zip": 92840,
    "Number1": 7145302337
  },
  {
    "FirstName": "DAVID",
    "LastName": "KAHN",
    "Address": "3570 Violet St",
    "Secondary Address": "",
    "City": "Seal Beach",
    "State": "CA",
    "County": "Orange",
    "Zip": 90740,
    "Number1": 5628108139
  },
  {
    "FirstName": "JAMES",
    "LastName": "HARMAN",
    "Address": "17342 Chestnut St",
    "Secondary Address": "",
    "City": "Yorba Linda",
    "State": "CA",
    "County": "Orange",
    "Zip": 92886,
    "Number1": 7143939659
  },
  {
    "FirstName": "ANTHONY",
    "LastName": "BECKING",
    "Address": "9592 Olympic Dr",
    "Secondary Address": "",
    "City": "Huntingtn Bch",
    "State": "CA",
    "County": "Orange",
    "Zip": 92646,
    "Number1": 9494005972
  },
  {
    "FirstName": "FRED",
    "LastName": "SMITH",
    "Address": "1300 Adams Ave",
    "Secondary Address": "",
    "City": "Costa Mesa",
    "State": "CA",
    "County": "Orange",
    "Zip": 92626,
    "Number1": 3109403158
  },
  {
    "FirstName": "CHRISTINE",
    "LastName": "VINCENT",
    "Address": "11179 Pioneer Ln",
    "Secondary Address": "",
    "City": "Garden Grove",
    "State": "CA",
    "County": "Orange",
    "Zip": 92840,
    "Number1": 7146360603
  },
  {
    "FirstName": "GREGG",
    "LastName": "TOBIN",
    "Address": "16 Victoria Ln",
    "Secondary Address": "",
    "City": "Trabuco Cyn",
    "State": "CA",
    "County": "Orange",
    "Zip": 92679,
    "Number1": 9498425673
  },
  {
    "FirstName": "BONI",
    "LastName": "GRAINGER",
    "Address": "30411 Alondra",
    "Secondary Address": "",
    "City": "Laguna Niguel",
    "State": "CA",
    "County": "Orange",
    "Zip": 92677,
    "Number1": 9492765291
  },
  {
    "FirstName": "DEBRA",
    "LastName": "JACOBSON",
    "Address": "180 Orangewood Ln",
    "Secondary Address": "",
    "City": "Tustin",
    "State": "CA",
    "County": "Orange",
    "Zip": 92780,
    "Number1": 7147428184
  },
  {
    "FirstName": "STEVE",
    "LastName": "MCKAY",
    "Address": "5601 Tiffany Ave",
    "Secondary Address": "",
    "City": "Garden Grove",
    "State": "CA",
    "County": "Orange",
    "Zip": 92845,
    "Number1": 7148936955
  },
  {
    "FirstName": "ROSE",
    "LastName": "BRICENO",
    "Address": "2619 W Rome Ave",
    "Secondary Address": "",
    "City": "Anaheim",
    "State": "CA",
    "County": "Orange",
    "Zip": 92804,
    "Number1": 7144968792
  },
  {
    "FirstName": "WILLIAM",
    "LastName": "CARPENTER",
    "Address": "627 W Valley View Dr",
    "Secondary Address": "",
    "City": "Fullerton",
    "State": "CA",
    "County": "Orange",
    "Zip": 92835,
    "Number1": 7147386415
  },
  {
    "FirstName": "ROBERT",
    "LastName": "LEFEBVRE",
    "Address": "600 W 4th Ave",
    "Secondary Address": "",
    "City": "La Habra",
    "State": "CA",
    "County": "Orange",
    "Zip": 90631,
    "Number1": 7142698292
  },
  {
    "FirstName": "PATSY",
    "LastName": "DEBOOY",
    "Address": "614 Sherwood Ave",
    "Secondary Address": "",
    "City": "Placentia",
    "State": "CA",
    "County": "Orange",
    "Zip": 92870,
    "Number1": 7148096399
  },
  {
    "FirstName": "WEBSTER",
    "LastName": "BOUCHER",
    "Address": "9092 Oasis Ave",
    "Secondary Address": "",
    "City": "Westminster",
    "State": "CA",
    "County": "Orange",
    "Zip": 92683,
    "Number1": 7145013231
  },
  {
    "FirstName": "BENEDICTA",
    "LastName": "NASRALLA",
    "Address": "8 Norton St",
    "Secondary Address": "",
    "City": "Irvine",
    "State": "CA",
    "County": "Orange",
    "Zip": 92612,
    "Number1": 9496334120
  },
  {
    "FirstName": "JULIE",
    "LastName": "HARRITY",
    "Address": "4 Briar Creek Ln",
    "Secondary Address": "",
    "City": "Laguna Hills",
    "State": "CA",
    "County": "Orange",
    "Zip": 92653,
    "Number1": 9497021290
  },
  {
    "FirstName": "WILHELMINA",
    "LastName": "BURGHARD",
    "Address": "6152 Bannock Rd",
    "Secondary Address": "",
    "City": "Westminster",
    "State": "CA",
    "County": "Orange",
    "Zip": 92683,
    "Number1": 7148922411
  },
  {
    "FirstName": "KELLY",
    "LastName": "ZUVER",
    "Address": "28081 Palmetto Ct",
    "Secondary Address": "",
    "City": "Laguna Niguel",
    "State": "CA",
    "County": "Orange",
    "Zip": 92677,
    "Number1": 9498742012
  },
  {
    "FirstName": "JOSEPH",
    "LastName": "SANTO",
    "Address": "40 Highpoint",
    "Secondary Address": "",
    "City": "Trabuco Cyn",
    "State": "CA",
    "County": "Orange",
    "Zip": 92679,
    "Number1": 7147660553
  },
  {
    "FirstName": "CHRISTINA",
    "LastName": "CRINER",
    "Address": "101 Colony Way",
    "Secondary Address": "",
    "City": "Aliso Viejo",
    "State": "CA",
    "County": "Orange",
    "Zip": 92656,
    "Number1": 7149577134
  },
  {
    "FirstName": "JEFFREY",
    "LastName": "CHELWICK",
    "Address": "7001 E Sundance Cir",
    "Secondary Address": "",
    "City": "Orange",
    "State": "CA",
    "County": "Orange",
    "Zip": 92869,
    "Number1": 7142898608
  },
  {
    "FirstName": "JUTTA",
    "LastName": "HECKHAUSEN",
    "Address": "8 Bartok Ct",
    "Secondary Address": "",
    "City": "Irvine",
    "State": "CA",
    "County": "Orange",
    "Zip": 92617,
    "Number1": 9493268096
  },
  {
    "FirstName": "RAMON",
    "LastName": "FAJARDO",
    "Address": "7197 Harding Cir",
    "Secondary Address": "",
    "City": "Buena Park",
    "State": "CA",
    "County": "Orange",
    "Zip": 90620,
    "Number1": 7148277560
  },
  {
    "FirstName": "MARIA",
    "LastName": "HOOD",
    "Address": "8541 Merle Cir",
    "Secondary Address": "",
    "City": "Huntingtn Bch",
    "State": "CA",
    "County": "Orange",
    "Zip": 92647,
    "Number1": 7145961940
  },
  {
    "FirstName": "TIMOTHY",
    "LastName": "BOND",
    "Address": "2450 Agnes Cir",
    "Secondary Address": "",
    "City": "Fullerton",
    "State": "CA",
    "County": "Orange",
    "Zip": 92835,
    "Number1": 7146729551
  },
  {
    "FirstName": "MATTHEW",
    "LastName": "BAER",
    "Address": "31131 Almara Ln",
    "Secondary Address": "",
    "City": "Laguna Niguel",
    "State": "CA",
    "County": "Orange",
    "Zip": 92677,
    "Number1": 6309042589
  },
  {
    "FirstName": "CHRISTINE",
    "LastName": "STONE",
    "Address": "4525 Guava Ave",
    "Secondary Address": "",
    "City": "Seal Beach",
    "State": "CA",
    "County": "Orange",
    "Zip": 90740,
    "Number1": 5625987516
  },
  {
    "FirstName": "DANIEL",
    "LastName": "MATSON",
    "Address": "2060 Newport Blvd",
    "Secondary Address": "",
    "City": "Costa Mesa",
    "State": "CA",
    "County": "Orange",
    "Zip": 92627,
    "Number1": 9496454314
  },
  {
    "FirstName": "DEBRA",
    "LastName": "HANEY",
    "Address": "7124 Santa Anita Cir",
    "Secondary Address": "",
    "City": "Buena Park",
    "State": "CA",
    "County": "Orange",
    "Zip": 90620,
    "Number1": 7147615346
  },
  {
    "FirstName": "DANIEL",
    "LastName": "PAYNE",
    "Address": "28675 Via Pasatiempo",
    "Secondary Address": "",
    "City": "Laguna Niguel",
    "State": "CA",
    "County": "Orange",
    "Zip": 92677,
    "Number1": 9496437856
  },
  {
    "FirstName": "SUSAN",
    "LastName": "ADAMS",
    "Address": "2341 Wilshire Ave",
    "Secondary Address": "",
    "City": "La Habra",
    "State": "CA",
    "County": "Orange",
    "Zip": 90631,
    "Number1": 5626915202
  },
  {
    "FirstName": "ANTONIO",
    "LastName": "CRUZ",
    "Address": "180 N Avenida Encina",
    "Secondary Address": "",
    "City": "Anaheim",
    "State": "CA",
    "County": "Orange",
    "Zip": 92807,
    "Number1": 7146372856
  },
  {
    "FirstName": "ELIZABETH",
    "LastName": "SAKAI",
    "Address": "25352 Gemini Ln",
    "Secondary Address": "",
    "City": "Lake Forest",
    "State": "CA",
    "County": "Orange",
    "Zip": 92630,
    "Number1": 7148377784
  },
  {
    "FirstName": "STACY",
    "LastName": "VIRGA",
    "Address": "21246 Burlington Ln",
    "Secondary Address": "",
    "City": "Huntingtn Bch",
    "State": "CA",
    "County": "Orange",
    "Zip": 92646,
    "Number1": 7149699807
  },
  {
    "FirstName": "LETICIA",
    "LastName": "GALVAN",
    "Address": "190 Lexington Ln",
    "Secondary Address": "",
    "City": "Costa Mesa",
    "State": "CA",
    "County": "Orange",
    "Zip": 92626,
    "Number1": 7142135345
  },
  {
    "FirstName": "KAREN",
    "LastName": "MORAN",
    "Address": "122 11th St",
    "Secondary Address": "",
    "City": "Huntingtn Bch",
    "State": "CA",
    "County": "Orange",
    "Zip": 92648,
    "Number1": 7149160563
  },
  {
    "FirstName": "VALERIE",
    "LastName": "CAUGHLIN",
    "Address": "18221 Allegheny Dr",
    "Secondary Address": "",
    "City": "Santa Ana",
    "State": "CA",
    "County": "Orange",
    "Zip": 92705,
    "Number1": 7143689411
  },
  {
    "FirstName": "LORI",
    "LastName": "DERMAN",
    "Address": "1 Faith",
    "Secondary Address": "",
    "City": "Irvine",
    "State": "CA",
    "County": "Orange",
    "Zip": 92612,
    "Number1": 9498545154
  },
  {
    "FirstName": "JOY CUC HOANG",
    "LastName": "TRUONG",
    "Address": "8152 20th St",
    "Secondary Address": "",
    "City": "Westminster",
    "State": "CA",
    "County": "Orange",
    "Zip": 92683,
    "Number1": 7142519604
  },
  {
    "FirstName": "DEBRA",
    "LastName": "DAVIS",
    "Address": "325 N Kathryn Dr",
    "Secondary Address": "",
    "City": "Anaheim",
    "State": "CA",
    "County": "Orange",
    "Zip": 92801,
    "Number1": 7149915019
  },
  {
    "FirstName": "LORRAINE",
    "LastName": "TREVINO",
    "Address": "5701 Stardust Dr",
    "Secondary Address": "",
    "City": "Huntingtn Bch",
    "State": "CA",
    "County": "Orange",
    "Zip": 92647,
    "Number1": 9496737427
  },
  {
    "FirstName": "NANCY",
    "LastName": "BINAGHI",
    "Address": "1333 Altura",
    "Secondary Address": "",
    "City": "San Clemente",
    "State": "CA",
    "County": "Orange",
    "Zip": 92673,
    "Number1": 9492918225
  },
  {
    "FirstName": "KYUNG",
    "LastName": "CHOI",
    "Address": "1750 N Cedar Glen Dr",
    "Secondary Address": "",
    "City": "Anaheim",
    "State": "CA",
    "County": "Orange",
    "Zip": 92807,
    "Number1": 7148635232
  },
  {
    "FirstName": "RHONDA",
    "LastName": "HUMMEL",
    "Address": "7 Marblehead Pl",
    "Secondary Address": "",
    "City": "Laguna Niguel",
    "State": "CA",
    "County": "Orange",
    "Zip": 92677,
    "Number1": 9492406439
  },
  {
    "FirstName": "SCOTT",
    "LastName": "ULRICH",
    "Address": "21526 Via Del Angel",
    "Secondary Address": "",
    "City": "Lake Forest",
    "State": "CA",
    "County": "Orange",
    "Zip": 92630,
    "Number1": 7143232933
  },
  {
    "FirstName": "KATHY",
    "LastName": "GUTTORMSON",
    "Address": "1049 S Verde St",
    "Secondary Address": "",
    "City": "Anaheim",
    "State": "CA",
    "County": "Orange",
    "Zip": 92805,
    "Number1": 7145631885
  },
  {
    "FirstName": "DANIEL",
    "LastName": "BOATRIGHT",
    "Address": "21952 Salcedo",
    "Secondary Address": "",
    "City": "Mission Viejo",
    "State": "CA",
    "County": "Orange",
    "Zip": 92691,
    "Number1": 9498598694
  },
  {
    "FirstName": "RAFAEL",
    "LastName": "JIMENEZ",
    "Address": "12312 Newport Ave",
    "Secondary Address": "",
    "City": "Santa Ana",
    "State": "CA",
    "County": "Orange",
    "Zip": 92705,
    "Number1": 7145448079
  },
  {
    "FirstName": "PAUL",
    "LastName": "HOLLIMON",
    "Address": "449 E Rosslynn Ave",
    "Secondary Address": "",
    "City": "Fullerton",
    "State": "CA",
    "County": "Orange",
    "Zip": 92832,
    "Number1": 7147388635
  },
  {
    "FirstName": "LORNA",
    "LastName": "FARNUM",
    "Address": "3305 Druid Ln",
    "Secondary Address": "",
    "City": "Los Alamitos",
    "State": "CA",
    "County": "Orange",
    "Zip": 90720,
    "Number1": 5627999648
  },
  {
    "FirstName": "SAWSSAN",
    "LastName": "NASSAR",
    "Address": "16408 San Gabriel St",
    "Secondary Address": "",
    "City": "Fountain Vly",
    "State": "CA",
    "County": "Orange",
    "Zip": 92708,
    "Number1": 7143171534
  },
  {
    "FirstName": "MARK",
    "LastName": "LOHRBACH",
    "Address": "33894 Cape Cv",
    "Secondary Address": "",
    "City": "Dana Point",
    "State": "CA",
    "County": "Orange",
    "Zip": 92629,
    "Number1": 9492805058
  },
  {
    "FirstName": "KARIN",
    "LastName": "WEAVER",
    "Address": "1204 Calle Toledo",
    "Secondary Address": "",
    "City": "San Clemente",
    "State": "CA",
    "County": "Orange",
    "Zip": 92672,
    "Number1": 9513130623
  },
  {
    "FirstName": "JA NECE",
    "LastName": "SIMPSON",
    "Address": "26546 Shane Dr",
    "Secondary Address": "",
    "City": "Lake Forest",
    "State": "CA",
    "County": "Orange",
    "Zip": 92630,
    "Number1": 9498307288
  },
  {
    "FirstName": "GAIL",
    "LastName": "EDMONDSON",
    "Address": "2650 Palmetto",
    "Secondary Address": "",
    "City": "Tustin",
    "State": "CA",
    "County": "Orange",
    "Zip": 92782,
    "Number1": 4156406521
  },
  {
    "FirstName": "LAURA",
    "LastName": "BUTTICE",
    "Address": "8045 E San Luis Dr",
    "Secondary Address": "",
    "City": "Orange",
    "State": "CA",
    "County": "Orange",
    "Zip": 92869,
    "Number1": 7145383445
  },
  {
    "FirstName": "DIANNE",
    "LastName": "TROGE",
    "Address": "863 S Nordica Ln",
    "Secondary Address": "",
    "City": "Anaheim",
    "State": "CA",
    "County": "Orange",
    "Zip": 92806,
    "Number1": 7148155145
  },
  {
    "FirstName": "DONALD",
    "LastName": "BARNES",
    "Address": "198 N Brea Blvd",
    "Secondary Address": "",
    "City": "Brea",
    "State": "CA",
    "County": "Orange",
    "Zip": 92821,
    "Number1": 7603262321
  },
  {
    "FirstName": "ANTONIO",
    "LastName": "LOPEZ",
    "Address": "2501 E Belmont Ct",
    "Secondary Address": "",
    "City": "Anaheim",
    "State": "CA",
    "County": "Orange",
    "Zip": 92806,
    "Number1": 7148650386
  },
  {
    "FirstName": "ERIC",
    "LastName": "COULTER",
    "Address": "19742 Canyon Dr",
    "Secondary Address": "",
    "City": "Yorba Linda",
    "State": "CA",
    "County": "Orange",
    "Zip": 92886,
    "Number1": 7145252044
  },
  {
    "FirstName": "RICHARD",
    "LastName": "MILLER",
    "Address": "2630 Rainier Way",
    "Secondary Address": "",
    "City": "La Habra",
    "State": "CA",
    "County": "Orange",
    "Zip": 90631,
    "Number1": 5629050034
  },
  {
    "FirstName": "DEAN",
    "LastName": "SMITH",
    "Address": "5001 Wagon Wheel Dr",
    "Secondary Address": "",
    "City": "Yorba Linda",
    "State": "CA",
    "County": "Orange",
    "Zip": 92886,
    "Number1": 7146950244
  },
  {
    "FirstName": "EFFIE",
    "LastName": "WOO",
    "Address": "21 Gramercy",
    "Secondary Address": "",
    "City": "Irvine",
    "State": "CA",
    "County": "Orange",
    "Zip": 92612,
    "Number1": 7142258641
  },
  {
    "FirstName": "LINDA",
    "LastName": "TUGGLE",
    "Address": "5595 Van Gogh Way",
    "Secondary Address": "",
    "City": "Yorba Linda",
    "State": "CA",
    "County": "Orange",
    "Zip": 92887,
    "Number1": 7143263644
  },
  {
    "FirstName": "MARK",
    "LastName": "JOSTEN",
    "Address": "2318 Coronado Dr",
    "Secondary Address": "",
    "City": "Fullerton",
    "State": "CA",
    "County": "Orange",
    "Zip": 92835,
    "Number1": 7145267606
  },
  {
    "FirstName": "CAROL",
    "LastName": "RUIZ",
    "Address": "22456 Estallens",
    "Secondary Address": "",
    "City": "Mission Viejo",
    "State": "CA",
    "County": "Orange",
    "Zip": 92692,
    "Number1": 9492926474
  },
  {
    "FirstName": "TERI",
    "LastName": "LAYMAN",
    "Address": "11 Gretel Ct",
    "Secondary Address": "",
    "City": "Newport Beach",
    "State": "CA",
    "County": "Orange",
    "Zip": 92663,
    "Number1": 9497221518
  },
  {
    "FirstName": "DANIEL",
    "LastName": "BONDARENKO",
    "Address": "26596 Somerly",
    "Secondary Address": "",
    "City": "Mission Viejo",
    "State": "CA",
    "County": "Orange",
    "Zip": 92692,
    "Number1": 9493679704
  },
  {
    "FirstName": "ALICIA",
    "LastName": "RODRIGUEZ",
    "Address": "2220 S Flower St",
    "Secondary Address": "",
    "City": "Santa Ana",
    "State": "CA",
    "County": "Orange",
    "Zip": 92707,
    "Number1": 7147517440
  },
  {
    "FirstName": "ARJANG",
    "LastName": "BAYGINEJAD",
    "Address": "19261 Sycamore Glen Dr",
    "Secondary Address": "",
    "City": "Trabuco Cyn",
    "State": "CA",
    "County": "Orange",
    "Zip": 92679,
    "Number1": 9497134413
  },
  {
    "FirstName": "RUFO",
    "LastName": "GARCIA",
    "Address": "2222 S Diamond St",
    "Secondary Address": "",
    "City": "Santa Ana",
    "State": "CA",
    "County": "Orange",
    "Zip": 92704,
    "Number1": 7145405036
  },
  {
    "FirstName": "ALLISON",
    "LastName": "WITTWER",
    "Address": "2809 S Fairview St",
    "Secondary Address": "",
    "City": "Santa Ana",
    "State": "CA",
    "County": "Orange",
    "Zip": 92704,
    "Number1": 7143179521
  },
  {
    "FirstName": "LORI",
    "LastName": "CARTWRIGHT",
    "Address": "26502 Anselmo",
    "Secondary Address": "",
    "City": "Mission Viejo",
    "State": "CA",
    "County": "Orange",
    "Zip": 92691,
    "Number1": 9493483767
  },
  {
    "FirstName": "PAMELA",
    "LastName": "ROTHMAN",
    "Address": "1708 Stanley Ave",
    "Secondary Address": "",
    "City": "Placentia",
    "State": "CA",
    "County": "Orange",
    "Zip": 92870,
    "Number1": 7144998996
  },
  {
    "FirstName": "TORI",
    "LastName": "CRISS",
    "Address": "8537 Acacia Dr",
    "Secondary Address": "",
    "City": "Cypress",
    "State": "CA",
    "County": "Orange",
    "Zip": 90630,
    "Number1": 7149287765
  },
  {
    "FirstName": "DUY",
    "LastName": "LE",
    "Address": "4058 Humboldt Ln",
    "Secondary Address": "",
    "City": "Yorba Linda",
    "State": "CA",
    "County": "Orange",
    "Zip": 92886,
    "Number1": 7147175558
  },
  {
    "FirstName": "TERRY",
    "LastName": "VOS",
    "Address": "8582 Kendor Dr",
    "Secondary Address": "",
    "City": "Buena Park",
    "State": "CA",
    "County": "Orange",
    "Zip": 90620,
    "Number1": 7144841868
  },
  {
    "FirstName": "HWA-SHING",
    "LastName": "CHEN",
    "Address": "17861 Arbor Ln",
    "Secondary Address": "",
    "City": "Irvine",
    "State": "CA",
    "County": "Orange",
    "Zip": 92612,
    "Number1": 6025732601
  },
  {
    "FirstName": "ROCHELLE",
    "LastName": "LOMBARD",
    "Address": "920 Glenhaven Dr",
    "Secondary Address": "",
    "City": "La Habra",
    "State": "CA",
    "County": "Orange",
    "Zip": 90631,
    "Number1": 5626913342
  },
  {
    "FirstName": "DIEU",
    "LastName": "HA",
    "Address": "15882 Rochester St",
    "Secondary Address": "",
    "City": "Westminster",
    "State": "CA",
    "County": "Orange",
    "Zip": 92683,
    "Number1": 7143213713
  },
  {
    "FirstName": "MINH",
    "LastName": "NGUYEN",
    "Address": "2155 S Troy St",
    "Secondary Address": "",
    "City": "Anaheim",
    "State": "CA",
    "County": "Orange",
    "Zip": 92802,
    "Number1": 7142042764
  },
  {
    "FirstName": "GREGORY",
    "LastName": "TANIELIAN",
    "Address": "49 Costa Brava",
    "Secondary Address": "",
    "City": "Laguna Niguel",
    "State": "CA",
    "County": "Orange",
    "Zip": 92677,
    "Number1": 8189866220
  },
  {
    "FirstName": "HASSAN",
    "LastName": "KHOYLOU",
    "Address": "28446 Via Nandina",
    "Secondary Address": "",
    "City": "Laguna Niguel",
    "State": "CA",
    "County": "Orange",
    "Zip": 92677,
    "Number1": 9494487490
  },
  {
    "FirstName": "THOMAS",
    "LastName": "POTTINGER",
    "Address": "27861 Encanto",
    "Secondary Address": "",
    "City": "Mission Viejo",
    "State": "CA",
    "County": "Orange",
    "Zip": 92692,
    "Number1": 9498305606
  },
  {
    "FirstName": "RENEE",
    "LastName": "HUFFINE",
    "Address": "3085 Yukon Ave",
    "Secondary Address": "",
    "City": "Costa Mesa",
    "State": "CA",
    "County": "Orange",
    "Zip": 92626,
    "Number1": 7142255055
  },
  {
    "FirstName": "KEN",
    "LastName": "GARCIA",
    "Address": "444 Poplar St",
    "Secondary Address": "",
    "City": "Laguna Beach",
    "State": "CA",
    "County": "Orange",
    "Zip": 92651,
    "Number1": 9493766992
  }
]